notebook_instrumentation/__init__.py
notebook_instrumentation/instrumentation.py
notebook_instrumentation-0.0.4.dist-info/METADATA
notebook_instrumentation-0.0.4.dist-info/WHEEL
notebook_instrumentation-0.0.4.dist-info/top_level.txt
notebook_instrumentation-0.0.4.dist-info/RECORD
